majormode/__init__.py
majormode/prosoponym.py
prosoponym-1.2.4.dist-info/LICENSE.md
prosoponym-1.2.4.dist-info/WHEEL
prosoponym-1.2.4.dist-info/METADATA
prosoponym-1.2.4.dist-info/RECORD
