Metadata-Version: 2.1
Name: prosoponym
Version: 1.2.4
Summary: Python library to manage personal names (in onomastic terminology also known as prosoponyms)
Home-page: https://github.com/majormode/prosoponym-python-library
License: SEE LICENSE IN <LICENSE.md>
Keywords: library,prosoponym,surname
Author: Daniel CAUNE
Author-email: daniel.caune@gmail.com
Requires-Python: >=3.9
Classifier: Development Status :: 5 - Production/Stable
Classifier: License :: Other/Proprietary License
Classifier: Operating System :: OS Independent
Classifier: Programming Language :: Python
Classifier: Programming Language :: Python :: 3
Classifier: Programming Language :: Python :: 3.9
Classifier: Programming Language :: Python :: 3.10
Classifier: Programming Language :: Python :: 3.11
Classifier: Topic :: Software Development :: Libraries
Requires-Dist: Unidecode (>=1.3,<2.0)
Requires-Dist: perseus-core-library (>=1.19,<2.0)
Project-URL: Repository, https://github.com/majormode/prosoponym-python-library
